{
	"names": [
		{
					"region": "default",
					"roman": "Fei Long"
				},
				{
					"region": "japan",
					"roman": "Fei Long",
					"original": "フェイロン"
				}
	],
	"images": {
		"face": "feilong-old.webp"
	},
	"moves": {
		"{normal-throws}": [
			{
				"name": "Gankaiho",
				"input": "{close} :b: {or} :f:+[MP] {or} [HP]"
			},
			{
				"name": "Shushugai",
				"input": "{close} :b: {or} :f:+[MK] {or} [HK]"
			}
		],
		"{unique-attacks}": [
			{
				"name": "Chokkarakusho",
				"input": ":b: {or} :f:+[MK]"
			},
			{
				"name": "Engekishu",
				"input": ":b: {or} :f:+[HK]"
			}
		],
		"{special-moves}": [
			{
				"name": "Rekkaken",
				"input": ":qcf:+[P] {upTo3x}"
			},
			{
				"name": "Shienkyaku",
				"input": ":rdp:+[K]"
			}
		]
	}
}